BCD.v
module BCD(clk,Load,rst_asyn,Din,Q,Q_out);

input clk,Load,rst_asyn; 
input [3:0]Din;
output [3:0]Q;
reg [3:0]Q;
output [7:0] Q_out;
reg [7:0] Q_out; 

always@ (posedge clk)begin
   if (!rst_asyn)
      Q <= 4'b0000; 
   else if(Load)
      Q <= Din;
   else if (Q == 9)
      Q <= 4'b0000;
   else
      Q <= Q +1;
end

always@(*) begin
     case (Q)
      4'b0000 : Q_out = 8'b11000000;
      4'b0001 : Q_out = 8'b11111001;
      4'b0010 : Q_out = 8'b10100100;
      4'b0011 : Q_out = 8'b10110000;
      4'b0100 : Q_out = 8'b10011001;
      4'b0101 : Q_out = 8'b10010010;
      4'b0110 : Q_out = 8'b10000010;
      4'b0111 : Q_out = 8'b11111000;
      4'b1000 : Q_out = 8'b10000000;
      4'b1001 : Q_out = 8'b10010000;
      4'b1010 : Q_out = 8'b10100000;
      4'b1011 : Q_out = 8'b10000011;
      4'b1100 : Q_out = 8'b10100111;
      4'b1101 : Q_out = 8'b10100001;
      4'b1110 : Q_out = 8'b10000100;
      4'b1111 : Q_out = 8'b11110001;
      default : Q_out = 8'b00000000;
     endcase
end
endmodule

BCD_tb.v
module BCD_tb;
 reg clk,rst_asyn,Load;
 reg [3:0]Din;
 wire[3:0]Q;
 wire[6:0]Q_out;
 parameter PERIOD = 20;
 parameter real DUTY_CYCLE=0.5;
 parameter OFFSET=0;
initial begin
    #OFFSET;
    forever begin
    clk=1'b1;
    #(PERIOD-(PERIOD*DUTY_CYCLE)) clk=1'b0;
    #(PERIOD*DUTY_CYCLE);
    end
end
initial begin
    Din=4'b0010;
    Load=1'b1;
    rst_asyn=1'b0;
    #5 rst_asyn=1'b1;
    #10 Load=1'b0;
    #50 rst_asyn=1'b1;
    #10 Load=1'b1;
    #5 rst_asyn=1'b0;
    #200 $finish;
end
initial begin
$dumpfile("BCD.vcd");
    $dumpvars(0,BCD_tb);
end
    BCD BCD_tb(
        .clk(clk),
        .rst_asyn(rst_asyn),
        .Load(Load),
        .Din(Din)
    );
endmodule

BCD.vcd
$date
	Thu May 05 16:02:17 2022
$end
$version
	Icarus Verilog
$end
$timescale
	1s
$end
$scope module BCD_tb $end
$scope module BCD_tb $end
$var wire 4 ! Din [3:0] $end
$var wire 1 " Load $end
$var wire 1 # clk $end
$var wire 1 $ rst_asyn $end
$var reg 4 % Q [3:0] $end
$var reg 8 & Q_out [7:0] $end
$upscope $end
$upscope $end
$enddefinitions $end
#0
$dumpvars
b11000000 &
b0 %
0$
1#
1"
b10 !
$end
#5
1$
#10
0#
#15
0"
#20
b11111001 &
b1 %
1#
#30
0#
#40
b10100100 &
b10 %
1#
#50
0#
#60
b10110000 &
b11 %
1#
#70
0#
#75
1"
#80
b11000000 &
b0 %
0$
1#
